README.md
setup.py
scrapyx_scraperapi_v2/__init__.py
scrapyx_scraperapi_v2/scraperapi.py
scrapyx_scraperapi_v2.egg-info/PKG-INFO
scrapyx_scraperapi_v2.egg-info/SOURCES.txt
scrapyx_scraperapi_v2.egg-info/dependency_links.txt
scrapyx_scraperapi_v2.egg-info/top_level.txt