Metadata-Version: 2.1
Name: scrapyx-scraperapi-v2
Version: 0.1.2
Summary: Scrapy scraperapi Proxy: scraperapi interfacing middleware for Scrapy
Home-page: https://github.com/tubndgit/scrapyx-scraperapi-v2
Author: Henry B.
Author-email: tubnd.younet@gmail.com
License: MIT
Download-URL: https://github.com/tubndgit/scrapyx-scraperapi-v2/archive/master.zip
Platform: UNKNOWN
Requires-Python: >=2.7
